autocash/__init__.py
autocash-0.3.dist-info/licenses/LICENSE.txt
autocash-0.3.dist-info/METADATA
autocash-0.3.dist-info/WHEEL
autocash-0.3.dist-info/top_level.txt
autocash-0.3.dist-info/RECORD
