Metadata-Version: 2.4
Name: autocash
Version: 0.3
Summary: AutoCash payments gateway lib
Home-page: https://github.com/LSEGITHUB/VFCashPython
Author: KingZero
Author-email: KingZero@darksidehost.com
License: MIT
Classifier: Programming Language :: Python :: 3
Classifier: License :: OSI Approved :: MIT License
Classifier: Operating System :: OS Independent
Requires-Python: >=3.6
License-File: LICENSE.txt
Requires-Dist: requests
Dynamic: author
Dynamic: author-email
Dynamic: classifier
Dynamic: description
Dynamic: description-content-type
Dynamic: home-page
Dynamic: license
Dynamic: license-file
Dynamic: requires-dist
Dynamic: requires-python
Dynamic: summary
